dfx_utils/__init__.py
dfx_utils/code.py
dfx_utils/es_helper.py
dfx_utils/helper.py
dfx_utils/klass_helper.py
dfx_utils/task_helper.py
dfx_utils/test.py
dfx_utils/time_helper.py
dfx_utils/api_work/__init__.py
dfx_utils/api_work/request.py
dfx_utils/api_work/settings.py
DfxHelper-0.0.35.dist-info/LICENSE
DfxHelper-0.0.35.dist-info/METADATA
DfxHelper-0.0.35.dist-info/WHEEL
DfxHelper-0.0.35.dist-info/top_level.txt
DfxHelper-0.0.35.dist-info/RECORD
