Metadata-Version: 2.1
Name: DfxHelper
Version: 0.0.35
Summary: 辅助工具
Home-page: https://www.baidu.com
Author: dfx
Author-email: 1817556010@qq.com
License: GPL
Platform: UNKNOWN
Requires-Python: >=3.6.0
